[{"template_id":164608,"submission_id":164608,"template_lines":2,"submission_lines":2,"true_lines":2,"recall":1.0,"precision":1.0,"f":1.0},{"template_id":164864,"submission_id":164864,"template_lines":2,"submission_lines":2,"true_lines":2,"recall":1.0,"precision":1.0,"f":1.0},{"template_id":164926,"submission_id":164926,"template_lines":2,"submission_lines":2,"true_lines":2,"recall":1.0,"precision":1.0,"f":1.0},{"template_id":165120,"submission_id":165120,"template_lines":2,"submission_lines":3,"true_lines":2,"recall":0.6666666666666666,"precision":1.0,"f":0.8},{"template_id":165122,"submission_id":165122,"template_lines":2,"submission_lines":3,"true_lines":2,"recall":0.6666666666666666,"precision":1.0,"f":0.8},{"template_id":165134,"submission_id":165134,"template_lines":2,"submission_lines":2,"true_lines":2,"recall":1.0,"precision":1.0,"f":1.0},{"template_id":165141,"submission_id":165141,"template_lines":2,"submission_lines":2,"true_lines":2,"recall":1.0,"precision":1.0,"f":1.0},{"template_id":165376,"submission_id":165376,"template_lines":2,"submission_lines":3,"true_lines":2,"recall":0.6666666666666666,"precision":1.0,"f":0.8},{"template_id":165380,"submission_id":165380,"template_lines":1,"submission_lines":1,"true_lines":1,"recall":1.0,"precision":1.0,"f":1.0}]